lib/__init__.py
lib/database.py
simple_mongo/__init__.py
simple_mongo/aggregator.py
simple_mongo/collection.py
simple_mongo/database.py
simple_mongo-0.1.0.dist-info/METADATA
simple_mongo-0.1.0.dist-info/WHEEL
simple_mongo-0.1.0.dist-info/top_level.txt
simple_mongo-0.1.0.dist-info/RECORD
