Metadata-Version: 2.2
Name: simple-mongo
Version: 0.1.0
Summary: A simple MongoDB module with less configuration
Author: Marjon Godito
Requires-Dist: pymongo
Requires-Dist: python-dotenv
Dynamic: author
Dynamic: description
Dynamic: description-content-type
Dynamic: requires-dist
Dynamic: summary
